alfalfa_client/__init__.py
alfalfa_client/alfalfa_client.py
alfalfa_client/lib.py
alfalfa_client-1.0.0.dist-info/LICENSE.txt
alfalfa_client-1.0.0.dist-info/METADATA
alfalfa_client-1.0.0.dist-info/WHEEL
alfalfa_client-1.0.0.dist-info/RECORD
