Metadata-Version: 2.3
Name: alfalfa-client
Version: 1.0.0
Summary: A standalone client for the NREL Alfalfa application
License: LICENSE.txt
Author: Kyle Benne
Author-email: kyle.benne@nrel.gov
Requires-Python: >=3.8
Classifier: License :: Other/Proprietary License
Classifier: Programming Language :: Python :: 3
Classifier: Programming Language :: Python :: 3.8
Classifier: Programming Language :: Python :: 3.9
Classifier: Programming Language :: Python :: 3.10
Classifier: Programming Language :: Python :: 3.11
Classifier: Programming Language :: Python :: 3.12
Classifier: Programming Language :: Python :: 3.13
Requires-Dist: requests-toolbelt (>=1.0,<1.1)
